{
    // See https://go.microsoft.com/fwlink/?LinkId=733558
    // for the documentation about the tasks.json format
    // this goes in your .vscode folder
    //"command": "python ${relativeFile}" opens your currently active file with python (or at least tries to..)
    "version": "2.0.0",
    "tasks": [
        {
            "label": "echo",
            "type": "shell",
            "command": "python ${relativeFile}",
            "group": {
                "kind": "build",
                "isDefault": true
            }
        }
    ]
}
